wmk/__init__.py
wmk/cli.py
wmk/client_messages.py
wmk/loader.py
wmk/media_consumer.py
wmk/messenger.py
wmk/packager.py
wmk/pipecat_transport.py
wmk/player.py
wmk/system_messages.py
wmk/world_messages.py
wmk-0.39.dist-info/licenses/LICENSE
wmk-0.39.dist-info/METADATA
wmk-0.39.dist-info/WHEEL
wmk-0.39.dist-info/entry_points.txt
wmk-0.39.dist-info/top_level.txt
wmk-0.39.dist-info/RECORD
