Metadata-Version: 2.4
Name: wmk
Version: 0.39
Summary: World Model Kit
Author: Journee
License: Apache-2.0
Project-URL: Homepage, https://github.com/journee-live/wmk
Project-URL: Changelog, https://github.com/journee-live/wmk/releases
Project-URL: Issues, https://github.com/journee-live/wmk/issues
Project-URL: CI, https://github.com/journee-live/wmk/actions
Classifier: License :: OSI Approved :: Apache Software License
Requires-Python: >=3.8
License-File: LICENSE
Requires-Dist: pyglet>=2.0.0
Requires-Dist: click>=8.0.0
Requires-Dist: urllib3>=2.3.0
Requires-Dist: tqdm>=4.67.0
Requires-Dist: numpy
Requires-Dist: typing-extensions>=4.12.2
Provides-Extra: media
Requires-Dist: pygobject>=3.50.0; extra == "media"
Provides-Extra: test
Requires-Dist: pygobject>=3.50.0; extra == "test"
Requires-Dist: pytest; extra == "test"
Requires-Dist: pytest-cov; extra == "test"
Requires-Dist: boto3; extra == "test"
Provides-Extra: dev
Requires-Dist: jsonschema-gentypes; extra == "dev"
Requires-Dist: sphinx; extra == "dev"
Requires-Dist: sphinx-rtd-theme; extra == "dev"
Requires-Dist: ruff==0.9.7; extra == "dev"
Provides-Extra: pipecat
Requires-Dist: pipecat-ai==0.0.76; extra == "pipecat"
Requires-Dist: opencv-python>=4.8.0; extra == "pipecat"
Requires-Dist: pygobject>=3.50.0; extra == "pipecat"
Requires-Dist: PyAudio>=0.2.14; extra == "pipecat"
Provides-Extra: s3
Requires-Dist: boto3; extra == "s3"
Dynamic: license-file
